Workbook

Sheet 粗利目標（100%・105%）
A1: Weekends 2027年度 月別の粗利目標（100%・105%）と報奨金
A2: 青字・黄色＝入力値。月の目標は「前年の売上構成比」版と「スマレジ予算の月比率」版の2つ。B10で判定に使う版を選び、黄色の「実績粗利」にスマレジ粗利（税抜）を入れると段階と報奨金が出る。
A4: 年間予算売上（税抜） | B4: 63000000 | C4: 社長案（売上6,300万円・粗利2,200万円・販管費2,000万円・経常利益170万円）
A5: 年間予算粗利 | B5: 22000000
A6: 予算粗利率 | B6: =B5/B4
A7: 第2段階のライン | B7: 1.05
A8: 報奨金 第1段階（店舗合計・月） | B8: 30000 | C8: 粗利が月の目標（100%）以上
A9: 報奨金 第2段階（店舗合計・月） | B9: 51000 | C9: 粗利が月の目標の105%以上
A10: 判定に使う目標（1=前年構成比版、2=スマレジ版） | B10: 1
A11: 月 | B11: 前年売上（参考） | C11: 前年構成比 | D11: 目標売上（参考） | E11: 粗利目標100%（構成比版） | F11: 粗利目標105%（構成比版） | G11: 粗利目標100%（スマレジ版） | H11: 粗利目標105%（スマレジ版） | I11: 実績粗利 | J11: 判定に使う100%目標 | K11: 粗利 予算比 | L11: 段階 | M11: 報奨金（店舗計）
A12: 2026年8月 | B12: 3040292 | C12: =B12/SUM($B$12:$B$23) | D12: =ROUND($B$4*C12,-3) | E12: =ROUND($B$5*C12,-3) | F12: =ROUND(E12*$B$7,-3) | G12: =ROUND($B$5*3500000/60000000,-3) | H12: =ROUND(G12*$B$7,-3) | J12: =IF($B$10=2,G12,E12) | K12: =IF(I12="","",I12/J12) | L12: =IF(I12="","",IF(I12>=ROUND(J12*$B$7,-3),2,IF(I12>=J12,1,0))) | M12: =IF(OR(L12="",L12=0),0,IF(L12=2,$B$9,$B$8))
A13: 9月 | B13: 3638478 | C13: =B13/SUM($B$12:$B$23) | D13: =ROUND($B$4*C13,-3) | E13: =ROUND($B$5*C13,-3) | F13: =ROUND(E13*$B$7,-3) | G13: =ROUND($B$5*4500000/60000000,-3) | H13: =ROUND(G13*$B$7,-3) | J13: =IF($B$10=2,G13,E13) | K13: =IF(I13="","",I13/J13) | L13: =IF(I13="","",IF(I13>=ROUND(J13*$B$7,-3),2,IF(I13>=J13,1,0))) | M13: =IF(OR(L13="",L13=0),0,IF(L13=2,$B$9,$B$8))
A14: 10月 | B14: 4934704 | C14: =B14/SUM($B$12:$B$23) | D14: =ROUND($B$4*C14,-3) | E14: =ROUND($B$5*C14,-3) | F14: =ROUND(E14*$B$7,-3) | G14: =ROUND($B$5*5500000/60000000,-3) | H14: =ROUND(G14*$B$7,-3) | J14: =IF($B$10=2,G14,E14) | K14: =IF(I14="","",I14/J14) | L14: =IF(I14="","",IF(I14>=ROUND(J14*$B$7,-3),2,IF(I14>=J14,1,0))) | M14: =IF(OR(L14="",L14=0),0,IF(L14=2,$B$9,$B$8))
A15: 11月 | B15: 5149749 | C15: =B15/SUM($B$12:$B$23) | D15: =ROUND($B$4*C15,-3) | E15: =ROUND($B$5*C15,-3) | F15: =ROUND(E15*$B$7,-3) | G15: =ROUND($B$5*5500000/60000000,-3) | H15: =ROUND(G15*$B$7,-3) | J15: =IF($B$10=2,G15,E15) | K15: =IF(I15="","",I15/J15) | L15: =IF(I15="","",IF(I15>=ROUND(J15*$B$7,-3),2,IF(I15>=J15,1,0))) | M15: =IF(OR(L15="",L15=0),0,IF(L15=2,$B$9,$B$8))
A16: 12月 | B16: 6820952 | C16: =B16/SUM($B$12:$B$23) | D16: =ROUND($B$4*C16,-3) | E16: =ROUND($B$5*C16,-3) | F16: =ROUND(E16*$B$7,-3) | G16: =ROUND($B$5*7000000/60000000,-3) | H16: =ROUND(G16*$B$7,-3) | J16: =IF($B$10=2,G16,E16) | K16: =IF(I16="","",I16/J16) | L16: =IF(I16="","",IF(I16>=ROUND(J16*$B$7,-3),2,IF(I16>=J16,1,0))) | M16: =IF(OR(L16="",L16=0),0,IF(L16=2,$B$9,$B$8))
A17: 2027年1月 | B17: 4850701 | C17: =B17/SUM($B$12:$B$23) | D17: =ROUND($B$4*C17,-3) | E17: =ROUND($B$5*C17,-3) | F17: =ROUND(E17*$B$7,-3) | G17: =ROUND($B$5*6000000/60000000,-3) | H17: =ROUND(G17*$B$7,-3) | J17: =IF($B$10=2,G17,E17) | K17: =IF(I17="","",I17/J17) | L17: =IF(I17="","",IF(I17>=ROUND(J17*$B$7,-3),2,IF(I17>=J17,1,0))) | M17: =IF(OR(L17="",L17=0),0,IF(L17=2,$B$9,$B$8))
A18: 2月 | B18: 2795656 | C18: =B18/SUM($B$12:$B$23) | D18: =ROUND($B$4*C18,-3) | E18: =ROUND($B$5*C18,-3) | F18: =ROUND(E18*$B$7,-3) | G18: =ROUND($B$5*3500000/60000000,-3) | H18: =ROUND(G18*$B$7,-3) | J18: =IF($B$10=2,G18,E18) | K18: =IF(I18="","",I18/J18) | L18: =IF(I18="","",IF(I18>=ROUND(J18*$B$7,-3),2,IF(I18>=J18,1,0))) | M18: =IF(OR(L18="",L18=0),0,IF(L18=2,$B$9,$B$8))
A19: 3月 | B19: 4419804 | C19: =B19/SUM($B$12:$B$23) | D19: =ROUND($B$4*C19,-3) | E19: =ROUND($B$5*C19,-3) | F19: =ROUND(E19*$B$7,-3) | G19: =ROUND($B$5*5500000/60000000,-3) | H19: =ROUND(G19*$B$7,-3) | J19: =IF($B$10=2,G19,E19) | K19: =IF(I19="","",I19/J19) | L19: =IF(I19="","",IF(I19>=ROUND(J19*$B$7,-3),2,IF(I19>=J19,1,0))) | M19: =IF(OR(L19="",L19=0),0,IF(L19=2,$B$9,$B$8))
A20: 4月 | B20: 3581469 | C20: =B20/SUM($B$12:$B$23) | D20: =ROUND($B$4*C20,-3) | E20: =ROUND($B$5*C20,-3) | F20: =ROUND(E20*$B$7,-3) | G20: =ROUND($B$5*4500000/60000000,-3) | H20: =ROUND(G20*$B$7,-3) | J20: =IF($B$10=2,G20,E20) | K20: =IF(I20="","",I20/J20) | L20: =IF(I20="","",IF(I20>=ROUND(J20*$B$7,-3),2,IF(I20>=J20,1,0))) | M20: =IF(OR(L20="",L20=0),0,IF(L20=2,$B$9,$B$8))
A21: 5月 | B21: 4799124 | C21: =B21/SUM($B$12:$B$23) | D21: =ROUND($B$4*C21,-3) | E21: =ROUND($B$5*C21,-3) | F21: =ROUND(E21*$B$7,-3) | G21: =ROUND($B$5*4500000/60000000,-3) | H21: =ROUND(G21*$B$7,-3) | J21: =IF($B$10=2,G21,E21) | K21: =IF(I21="","",I21/J21) | L21: =IF(I21="","",IF(I21>=ROUND(J21*$B$7,-3),2,IF(I21>=J21,1,0))) | M21: =IF(OR(L21="",L21=0),0,IF(L21=2,$B$9,$B$8))
A22: 6月 | B22: 4888307 | C22: =B22/SUM($B$12:$B$23) | D22: =ROUND($B$4*C22,-3) | E22: =ROUND($B$5*C22,-3) | F22: =ROUND(E22*$B$7,-3) | G22: =ROUND($B$5*5500000/60000000,-3) | H22: =ROUND(G22*$B$7,-3) | J22: =IF($B$10=2,G22,E22) | K22: =IF(I22="","",I22/J22) | L22: =IF(I22="","",IF(I22>=ROUND(J22*$B$7,-3),2,IF(I22>=J22,1,0))) | M22: =IF(OR(L22="",L22=0),0,IF(L22=2,$B$9,$B$8))
A23: 7月 | B23: 4741065 | C23: =B23/SUM($B$12:$B$23) | D23: =ROUND($B$4*C23,-3) | E23: =ROUND($B$5*C23,-3) | F23: =ROUND(E23*$B$7,-3) | G23: =ROUND($B$5*4500000/60000000,-3) | H23: =ROUND(G23*$B$7,-3) | J23: =IF($B$10=2,G23,E23) | K23: =IF(I23="","",I23/J23) | L23: =IF(I23="","",IF(I23>=ROUND(J23*$B$7,-3),2,IF(I23>=J23,1,0))) | M23: =IF(OR(L23="",L23=0),0,IF(L23=2,$B$9,$B$8))
A24: 年計 | B24: =SUM(B12:B23) | C24: =SUM(C12:C23) | D24: =SUM(D12:D23) | E24: =SUM(E12:E23) | F24: =SUM(F12:F23) | G24: =SUM(G12:G23) | H24: =SUM(H12:H23) | I24: =SUM(I12:I23) | J24: =SUM(J12:J23) | M24: =SUM(M12:M23)
A25: 全月達成した場合の報奨金（年） | E25: =B8*12 | F25: =B9*12
A26: 前年構成比＝2025/8〜2026/7の月別売上（発展会計）の比率。会計の月次粗利は棚卸の調整で振れる（1月−124万円）ため、配分には売上の比率を使う。千円単位の丸めで年計が±1千円ずれることがある。
A27: 1人あたりの月額（店舗計を配分）
A28: 区分 | B28: 人数 | C28: 配分の重み | D28: 第1段階（円） | E28: 第2段階（円）
A29: 店長 | B29: 1 | C29: 25 | D29: =ROUND($B$8*C29/SUMPRODUCT($B$29:$B$31,$C$29:$C$31),-2) | E29: =ROUND($B$9*C29/SUMPRODUCT($B$29:$B$31,$C$29:$C$31),-2)
A30: 古参パート | B30: 1 | C30: 20 | D30: =ROUND($B$8*C30/SUMPRODUCT($B$29:$B$31,$C$29:$C$31),-2) | E30: =ROUND($B$9*C30/SUMPRODUCT($B$29:$B$31,$C$29:$C$31),-2)
A31: その他パート | B31: 3 | C31: 10 | D31: =ROUND($B$8*C31/SUMPRODUCT($B$29:$B$31,$C$29:$C$31),-2) | E31: =ROUND($B$9*C31/SUMPRODUCT($B$29:$B$31,$C$29:$C$31),-2)
A32: 合計（月） | D32: =SUMPRODUCT(B29:B31,D29:D31) | E32: =SUMPRODUCT(B29:B31,E29:E31)
A34: 考え方：第1段階（月3万円・年36万円）は予算達成時の経常利益の約半分。第2段階は、105%達成で増える利益（年約88万円）の約3割を上乗せした額（月5.1万円・年61万円）。
A35: 判定は粗利額のみ（売上は参考）。粗利目標は千円単位で丸め。処分品は粗利の計算から除く。

Sheet 前提
A1: Weekends 2027年度（2026/8〜2027/7）予算と報奨金 前提条件
A2: 青字＝入力値（変えると全シートが再計算）／黄色＝経営判断で決める値／黒字＝計算式。金額は税抜・円。
A4: 項目 | B4: 値 | C4: 出所・備考
A5: 年間予算売上（税抜） | B5: 60000000 | C5: スマレジ登録の店舗予算（ユーザー確認：税抜）
A6: 目標粗利率 | B6: 0.35 | C6: 9/22経営者指示。前年31.0%・前々年34.3%
A7: テナント経費の売上連動率 | B7: 0.0692 | C7: 売上歩合制（ユーザー確認）。2025/8〜2026/7の月次12点の回帰、決定係数0.94
A8: テナント経費の固定分（月） | B8: 209792 | C8: 同上の回帰の切片（共益費などの定額分とみなす）
A9: 店舗の固定経費（年） | B9: 3493268 | C9: 発展会計 営業部の販管費972.4万からテナント経費623.0万を除いた額
A10: 給与合計（月） | B10: 639029 | C10: 8/16〜9/15の給与実績（中川・小部・八木・島の4名）
A11: 社保加入者の給与（月） | B11: 544094 | C11: 中川＋小部（社会保険加入と仮定）
A12: 賞与（年） | B12: 770000 | C12: 今年も77万円（ユーザー確認）
A13: 法定福利の料率 | B13: 0.155 | C13: 仮置き。社保加入者の給与と賞与に掛ける
A14: 共通部の実費（年） | B14: 943852 | C14: 発展会計 全社−営業部−人件費。主に租税公課（3月・7月）
A15: 本部費（月） | B15: 158000 | C15: 管理会計シートの共通費。グループ共通費5,422万円の人員割（グラン2人／57.5人）
A16: 前年売上（2025/8〜2026/7） | B16: 53660301 | C16: 発展会計 全社 税抜
... A18: 営業日数（年） | B18: 313 | C18: 水曜定休の場合。前年は269日（記憶ベース・未確認）
A19: 参考：人件費の積み上げ（年） | B19: =B10*12+B12+(B11*12+B12)*B13 | C19: 給与×12＋賞与＋法定福利。採用値は26行目の月額×12
A20: 計算値
A21: 人件費（年） | B21: =B26*12 | C21: 26行目の月額×12（年960万円）
A22: 固定費：新体制の実費（年） | B22: =B9+B8*12+B21+B14 | C22: 店舗の固定経費＋テナント固定分＋人件費＋共通部の実費
A23: 固定費：本部費込み（年） | B23: =B9+B8*12+B21+B15*12 | C23: 共通部の実費を本部費（月額×12）に置き換え
A24: 限界利益率 | B24: =B6-B7 | C24: 粗利率−テナント連動率。売上1円の上積みで残る割合
A25: 予算粗利（年） | B25: =B5*B6
A26: 人件費（月・1か月分に平準化） | B26: 800000 | C26: 年960万円÷12（経営判断で指定）。賞与月も含め毎月同額で計上。参考：給与×12＋賞与＋法定福利の積み上げは下の行
A27: 報奨金の金額表（1人あたり月額・円）
A28: 区分 | B28: 人数 | C28: 第1段階 | D28: 第2段階 | E28: 第3段階
A29: 店長 | B29: 1 | C29: 8000 | D29: 13000 | E29: 18000
A30: 古参パート | B30: 1 | C30: 7000 | D30: 10000 | E30: 13000
A31: その他パート | B31: 3 | C31: 3000 | D31: 5000 | E31: 7000
A32: 店舗合計（月） | C32: =SUMPRODUCT($B$29:$B$31,C29:C31) | D32: =SUMPRODUCT($B$29:$B$31,D29:D31) | E32: =SUMPRODUCT($B$29:$B$31,E29:E31)
A33: 店舗合計（年・全月同じ段階） | C33: =C32*12 | D33: =D32*12 | E33: =E32*12
A35: 段階の判定（予算比）
A36: 段階 | B36: 予算比（以上） | C36: 備考
A37: 第1段階 | B37: 1 | C37: 損益分岐＋報奨金とほぼ同じ水準
A38: 第2段階 | B38: 1.05
A39: 第3段階 | B39: 1.1 | C39: 本部費込みでも黒字になる水準
A40: 判定ルール：スコア＝粗利額の予算比×80%＋売上の予算比×20%。ただし粗利額が予算未達なら0円。判定は毎月、支払いは夏冬の賞与にまとめる案。

Sheet 固変分解
A1: 固定費と変動費の分解（前年実績 → 今年の見込み）
A3: 勘定科目 | B3: 前年実績（年・円） | C3: 区分 | D3: 判断の根拠 | E3: 今年の見込み（年・円）
A4: 売上原価 | B4: 37048155 | C4: 変動 | D4: 売上×（1−粗利率） | E4: =前提!B5*(1-前提!B6)
A5: テナント経費（連動分） | B5: 3713272 | C5: 変動 | D5: 売上歩合制（確認済み）。回帰で売上の6.92% | E5: =前提!B5*前提!B7
A6: テナント経費（固定分） | B6: 2517504 | C6: 固定 | D6: 売上の少ない月ほど比率が高い（2月16.1%、12月10.3%）ため定額分とみる | E6: =前提!B8*12
A7: 人件費（給与・賞与・法定福利） | B7: 8091567 | C7: 固定 | D7: 売上と連動なし（決定係数0.13） | E7: =前提!B21
A8: 管理諸費 | B8: 1740717 | C8: 固定（要確認） | D8: やや売上と連動（決定係数0.10）、11月に398,379円。カード手数料を含むなら変動費へ | E8: 1740717
A9: 租税公課 | B9: 907400 | C9: 固定（要確認） | D9: 3月436,200・7月446,300円（共通部）。消費税の納付なら売上連動へ | E9: 907400
A10: 減価償却費 | B10: 529231 | C10: 固定 | D10: 毎月44,000円 | E10: 529231
A11: 旅費交通費 | B11: 374053 | C11: 固定 | D11: 仕入・展示会の出張費（確認済み） | E11: 374053
A12: システム関連費 | B12: 237018 | C12: 固定 | D12: 毎月17,500円 | E12: 237018
A13: 消耗品費 | B13: 180747 | C13: 固定 | D13: 売上と連動なし | E13: 180747
A14: 通信費 | B14: 170618 | C14: 固定 | D14: 毎月0.9〜1.9万円 | E14: 170618
A15: 広告宣伝費 | B15: 141719 | C15: 固定 | D15: 使う月を決めて出す費用 | E15: 141719
A16: 保険料 | B16: 130020 | C16: 固定 | D16: 10月に年額計上 | E16: 130020
A17: その他（交際費・寄付金・雑費） | B17: 25597 | C17: 固定 | D17: 少額 | E17: 25597
A19: 固定費の計 | B19: =SUMIF(C4:C17,"固定*",B4:B17) | D19: 本部費は含まない。前提シートの「新体制の実費」と一致するか確認： | E19: =SUMIF(C4:C17,"固定*",E4:E17)
A20: 照合：前提シートの固定費（新体制の実費） | E20: =前提!B22
A21: 差（0なら一致） | E21: =E19-E20
A23: 前年の固定費の計は、人件費を前年実額（809.2万円）で計算した値。前年実績は発展会計 全社PL（2025/8〜2026/7、税抜）。

Sheet 損益分岐
A1: 損益分岐点の段階（粗利率は前提シートの値）
A3: 段階 | B3: 年間の固定費 | C3: 必要な粗利額 | D3: 損益分岐の売上 | E3: 予算比 | F3: 前年比 | G3: 月平均の売上
A4: ① 前年体制の実費（人件費 809.2万円） | B4: =前提!B9+前提!B8*12+8091567+前提!B14 | C4: =D4*前提!$B$6 | D4: =B4/前提!$B$24 | E4: =D4/前提!$B$5 | F4: =D4/前提!$B$16 | G4: =D4/12
A5: ② 新体制の実費 | B5: =前提!B22 | C5: =D5*前提!$B$6 | D5: =B5/前提!$B$24 | E5: =D5/前提!$B$5 | F5: =D5/前提!$B$16 | G5: =D5/12
A6: ③ ②＋報奨金（第1段階） | B6: =前提!B22+前提!C33 | C6: =D6*前提!$B$6 | D6: =B6/前提!$B$24 | E6: =D6/前提!$B$5 | F6: =D6/前提!$B$16 | G6: =D6/12
A7: ④ ②＋本部費 | B7: =前提!B23 | C7: =D7*前提!$B$6 | D7: =B7/前提!$B$24 | E7: =D7/前提!$B$5 | F7: =D7/前提!$B$16 | G7: =D7/12
A8: ⑤ 管理会計シートの定額（人件費85万円/月＋本部費） | B8: =前提!B9+前提!B8*12+10200000+前提!B15*12 | C8: =D8*前提!$B$6 | D8: =B8/前提!$B$24 | E8: =D8/前提!$B$5 | F8: =D8/前提!$B$16 | G8: =D8/12
A10: 予算の売上で黒字に必要な粗利率（新体制の実費） | D10: =前提!B22/前提!B5+前提!B7
A11: 同（本部費込み） | D11: =前提!B23/前提!B5+前提!B7
A12: 粗利率31%のまま予算どおり売った場合の営業損益（新体制の実費） | D12: =(0.31-前提!B7)*前提!B5-前提!B22
A13: 粗利率1ポイントの価値（予算売上時・年） | D13: =前提!B5*0.01
A14: 売上100万円の上積みで残る利益 | D14: =1000000*前提!B24
A16: 損益分岐の売上＝固定費÷限界利益率（粗利率−テナント連動率）。

Sheet 予算比シミュレーション
A1: 予算比ごとの年間損益（全月同じ予算比・粗利率は前提シートの値）
A2: 黄色の予算比を書き換えると下の行がすべて変わる。報奨金は段階表の年額。
A4: 予算比 | B4: 売上 | C4: 粗利 | D4: 段階 | E4: 報奨金（年） | F4: 報奨金前 営業損益（新体制の実費） | G4: 報奨金後 営業損益（新体制の実費） | H4: 報奨金後 営業損益（本部費込み）
A5: 0.95 | B5: =前提!$B$5*A5 | C5: =B5*前提!$B$6 | D5: =IF(A5>=前提!$B$39,3,IF(A5>=前提!$B$38,2,IF(A5>=前提!$B$37,1,0))) | E5: =IF(D5=0,0,INDEX(前提!$C$33:$E$33,1,D5)) | F5: =C5-B5*前提!$B$7-前提!$B$22 | G5: =F5-E5 | H5: =C5-B5*前提!$B$7-前提!$B$23-E5
A6: 1 | B6: =前提!$B$5*A6 | C6: =B6*前提!$B$6 | D6: =IF(A6>=前提!$B$39,3,IF(A6>=前提!$B$38,2,IF(A6>=前提!$B$37,1,0))) | E6: =IF(D6=0,0,INDEX(前提!$C$33:$E$33,1,D6)) | F6: =C6-B6*前提!$B$7-前提!$B$22 | G6: =F6-E6 | H6: =C6-B6*前提!$B$7-前提!$B$23-E6
A7: 1.05 | B7: =前提!$B$5*A7 | C7: =B7*前提!$B$6 | D7: =IF(A7>=前提!$B$39,3,IF(A7>=前提!$B$38,2,IF(A7>=前提!$B$37,1,0))) | E7: =IF(D7=0,0,INDEX(前提!$C$33:$E$33,1,D7)) | F7: =C7-B7*前提!$B$7-前提!$B$22 | G7: =F7-E7 | H7: =C7-B7*前提!$B$7-前提!$B$23-E7
A8: 1.1 | B8: =前提!$B$5*A8 | C8: =B8*前提!$B$6 | D8: =IF(A8>=前提!$B$39,3,IF(A8>=前提!$B$38,2,IF(A8>=前提!$B$37,1,0))) | E8: =IF(D8=0,0,INDEX(前提!$C$33:$E$33,1,D8)) | F8: =C8-B8*前提!$B$7-前提!$B$22 | G8: =F8-E8 | H8: =C8-B8*前提!$B$7-前提!$B$23-E8
A9: 1.15 | B9: =前提!$B$5*A9 | C9: =B9*前提!$B$6 | D9: =IF(A9>=前提!$B$39,3,IF(A9>=前提!$B$38,2,IF(A9>=前提!$B$37,1,0))) | E9: =IF(D9=0,0,INDEX(前提!$C$33:$E$33,1,D9)) | F9: =C9-B9*前提!$B$7-前提!$B$22 | G9: =F9-E9 | H9: =C9-B9*前提!$B$7-前提!$B$23-E9
A11: 粗利率だけ変えた場合（売上は予算どおり）
A12: 粗利率 | B12: 粗利 | C12: 報奨金前 営業損益（新体制の実費） | D12: 同（本部費込み）
A13: 0.31 | B13: =前提!$B$5*A13 | C13: =前提!$B$5*(A13-前提!$B$7)-前提!$B$22 | D13: =前提!$B$5*(A13-前提!$B$7)-前提!$B$23
A14: 0.33 | B14: =前提!$B$5*A14 | C14: =前提!$B$5*(A14-前提!$B$7)-前提!$B$22 | D14: =前提!$B$5*(A14-前提!$B$7)-前提!$B$23
A15: 0.345 | B15: =前提!$B$5*A15 | C15: =前提!$B$5*(A15-前提!$B$7)-前提!$B$22 | D15: =前提!$B$5*(A15-前提!$B$7)-前提!$B$23
A16: 0.35 | B16: =前提!$B$5*A16 | C16: =前提!$B$5*(A16-前提!$B$7)-前提!$B$22 | D16: =前提!$B$5*(A16-前提!$B$7)-前提!$B$23
A17: 0.36 | B17: =前提!$B$5*A17 | C17: =前提!$B$5*(A17-前提!$B$7)-前提!$B$22 | D17: =前提!$B$5*(A17-前提!$B$7)-前提!$B$23
A18: 0.37 | B18: =前提!$B$5*A18 | C18: =前提!$B$5*(A18-前提!$B$7)-前提!$B$22 | D18: =前提!$B$5*(A18-前提!$B$7)-前提!$B$23

Sheet 月別目標と判定
A1: 月別の予算と報奨金の判定（黄色に毎月のスマレジ実績を入れる・税抜）
A3: 月 | B3: 予算売上 | C3: 予算粗利 | D3: 実績売上 | E3: 実績粗利 | F3: 粗利 予算比 | G3: 売上 予算比 | H3: スコア | I3: 段階 | J3: 報奨金 | K3: 営業損益（新体制の実費・報奨金後） | L3: 累計
A4: 2026年8月 | B4: =前提!$B$5*3500000/60000000 | C4: =B4*前提!$B$6 | F4: =IF(E4="","",E4/C4) | G4: =IF(D4="","",D4/B4) | H4: =IF(OR(D4="",E4=""),"",F4*0.8+G4*0.2) | I4: =IF(H4="","",IF(F4<前提!$B$37,0,IF(H4>=前提!$B$39,3,IF(H4>=前提!$B$38,2,IF(H4>=前提!$B$37,1,0))))) | J4: =IF(OR(I4="",I4=0),0,INDEX(前提!$C$32:$E$32,1,I4)) | K4: =IF(E4="","",E4-D4*前提!$B$7-前提!$B$22/12-J4) | L4: =IF(K4="","",SUM($K$4:K4))
A5: 9月 | B5: =前提!$B$5*4500000/60000000 | C5: =B5*前提!$B$6 | F5: =IF(E5="","",E5/C5) | G5: =IF(D5="","",D5/B5) | H5: =IF(OR(D5="",E5=""),"",F5*0.8+G5*0.2) | I5: =IF(H5="","",IF(F5<前提!$B$37,0,IF(H5>=前提!$B$39,3,IF(H5>=前提!$B$38,2,IF(H5>=前提!$B$37,1,0))))) | J5: =IF(OR(I5="",I5=0),0,INDEX(前提!$C$32:$E$32,1,I5)) | K5: =IF(E5="","",E5-D5*前提!$B$7-前提!$B$22/12-J5) | L5: =IF(K5="","",SUM($K$4:K5))
A6: 10月 | B6: =前提!$B$5*5500000/60000000 | C6: =B6*前提!$B$6 | F6: =IF(E6="","",E6/C6) | G6: =IF(D6="","",D6/B6) | H6: =IF(OR(D6="",E6=""),"",F6*0.8+G6*0.2) | I6: =IF(H6="","",IF(F6<前提!$B$37,0,IF(H6>=前提!$B$39,3,IF(H6>=前提!$B$38,2,IF(H6>=前提!$B$37,1,0))))) | J6: =IF(OR(I6="",I6=0),0,INDEX(前提!$C$32:$E$32,1,I6)) | K6: =IF(E6="","",E6-D6*前提!$B$7-前提!$B$22/12-J6) | L6: =IF(K6="","",SUM($K$4:K6))
A7: 11月 | B7: =前提!$B$5*5500000/60000000 | C7: =B7*前提!$B$6 | F7: =IF(E7="","",E7/C7) | G7: =IF(D7="","",D7/B7) | H7: =IF(OR(D7="",E7=""),"",F7*0.8+G7*0.2) | I7: =IF(H7="","",IF(F7<前提!$B$37,0,IF(H7>=前提!$B$39,3,IF(H7>=前提!$B$38,2,IF(H7>=前提!$B$37,1,0))))) | J7: =IF(OR(I7="",I7=0),0,INDEX(前提!$C$32:$E$32,1,I7)) | K7: =IF(E7="","",E7-D7*前提!$B$7-前提!$B$22/12-J7) | L7: =IF(K7="","",SUM($K$4:K7))
A8: 12月 | B8: =前提!$B$5*7000000/60000000 | C8: =B8*前提!$B$6 | F8: =IF(E8="","",E8/C8) | G8: =IF(D8="","",D8/B8) | H8: =IF(OR(D8="",E8=""),"",F8*0.8+G8*0.2) | I8: =IF(H8="","",IF(F8<前提!$B$37,0,IF(H8>=前提!$B$39,3,IF(H8>=前提!$B$38,2,IF(H8>=前提!$B$37,1,0))))) | J8: =IF(OR(I8="",I8=0),0,INDEX(前提!$C$32:$E$32,1,I8)) | K8: =IF(E8="","",E8-D8*前提!$B$7-前提!$B$22/12-J8) | L8: =IF(K8="","",SUM($K$4:K8))
A9: 2027年1月 | B9: =前提!$B$5*6000000/60000000 | C9: =B9*前提!$B$6 | F9: =IF(E9="","",E9/C9) | G9: =IF(D9="","",D9/B9) | H9: =IF(OR(D9="",E9=""),"",F9*0.8+G9*0.2) | I9: =IF(H9="","",IF(F9<前提!$B$37,0,IF(H9>=前提!$B$39,3,IF(H9>=前提!$B$38,2,IF(H9>=前提!$B$37,1,0))))) | J9: =IF(OR(I9="",I9=0),0,INDEX(前提!$C$32:$E$32,1,I9)) | K9: =IF(E9="","",E9-D9*前提!$B$7-前提!$B$22/12-J9) | L9: =IF(K9="","",SUM($K$4:K9))
A10: 2月 | B10: =前提!$B$5*3500000/60000000 | C10: =B10*前提!$B$6 | F10: =IF(E10="","",E10/C10) | G10: =IF(D10="","",D10/B10) | H10: =IF(OR(D10="",E10=""),"",F10*0.8+G10*0.2) | I10: =IF(H10="","",IF(F10<前提!$B$37,0,IF(H10>=前提!$B$39,3,IF(H10>=前提!$B$38,2,IF(H10>=前提!$B$37,1,0))))) | J10: =IF(OR(I10="",I10=0),0,INDEX(前提!$C$32:$E$32,1,I10)) | K10: =IF(E10="","",E10-D10*前提!$B$7-前提!$B$22/12-J10) | L10: =IF(K10="","",SUM($K$4:K10))
A11: 3月 | B11: =前提!$B$5*5500000/60000000 | C11: =B11*前提!$B$6 | F11: =IF(E11="","",E11/C11) | G11: =IF(D11="","",D11/B11) | H11: =IF(OR(D11="",E11=""),"",F11*0.8+G11*0.2) | I11: =IF(H11="","",IF(F11<前提!$B$37,0,IF(H11>=前提!$B$39,3,IF(H11>=前提!$B$38,2,IF(H11>=前提!$B$37,1,0))))) | J11: =IF(OR(I11="",I11=0),0,INDEX(前提!$C$32:$E$32,1,I11)) | K11: =IF(E11="","",E11-D11*前提!$B$7-前提!$B$22/12-J11) | L11: =IF(K11="","",SUM($K$4:K11))
A12: 4月 | B12: =前提!$B$5*4500000/60000000 | C12: =B12*前提!$B$6 | F12: =IF(E12="","",E12/C12) | G12: =IF(D12="","",D12/B12) | H12: =IF(OR(D12="",E12=""),"",F12*0.8+G12*0.2) | I12: =IF(H12="","",IF(F12<前提!$B$37,0,IF(H12>=前提!$B$39,3,IF(H12>=前提!$B$38,2,IF(H12>=前提!$B$37,1,0))))) | J12: =IF(OR(I12="",I12=0),0,INDEX(前提!$C$32:$E$32,1,I12)) | K12: =IF(E12="","",E12-D12*前提!$B$7-前提!$B$22/12-J12) | L12: =IF(K12="","",SUM($K$4:K12))
A13: 5月 | B13: =前提!$B$5*4500000/60000000 | C13: =B13*前提!$B$6 | F13: =IF(E13="","",E13/C13) | G13: =IF(D13="","",D13/B13) | H13: =IF(OR(D13="",E13=""),"",F13*0.8+G13*0.2) | I13: =IF(H13="","",IF(F13<前提!$B$37,0,IF(H13>=前提!$B$39,3,IF(H13>=前提!$B$38,2,IF(H13>=前提!$B$37,1,0))))) | J13: =IF(OR(I13="",I13=0),0,INDEX(前提!$C$32:$E$32,1,I13)) | K13: =IF(E13="","",E13-D13*前提!$B$7-前提!$B$22/12-J13) | L13: =IF(K13="","",SUM($K$4:K13))
A14: 6月 | B14: =前提!$B$5*5500000/60000000 | C14: =B14*前提!$B$6 | F14: =IF(E14="","",E14/C14) | G14: =IF(D14="","",D14/B14) | H14: =IF(OR(D14="",E14=""),"",F14*0.8+G14*0.2) | I14: =IF(H14="","",IF(F14<前提!$B$37,0,IF(H14>=前提!$B$39,3,IF(H14>=前提!$B$38,2,IF(H14>=前提!$B$37,1,0))))) | J14: =IF(OR(I14="",I14=0),0,INDEX(前提!$C$32:$E$32,1,I14)) | K14: =IF(E14="","",E14-D14*前提!$B$7-前提!$B$22/12-J14) | L14: =IF(K14="","",SUM($K$4:K14))
A15: 7月 | B15: =前提!$B$5*4500000/60000000 | C15: =B15*前提!$B$6 | F15: =IF(E15="","",E15/C15) | G15: =IF(D15="","",D15/B15) | H15: =IF(OR(D15="",E15=""),"",F15*0.8+G15*0.2) | I15: =IF(H15="","",IF(F15<前提!$B$37,0,IF(H15>=前提!$B$39,3,IF(H15>=前提!$B$38,2,IF(H15>=前提!$B$37,1,0))))) | J15: =IF(OR(I15="",I15=0),0,INDEX(前提!$C$32:$E$32,1,I15)) | K15: =IF(E15="","",E15-D15*前提!$B$7-前提!$B$22/12-J15) | L15: =IF(K15="","",SUM($K$4:K15))
A16: 年計 | B16: =SUM(B4:B15) | C16: =SUM(C4:C15) | D16: =SUM(D4:D15) | E16: =SUM(E4:E15) | J16: =SUM(J4:J15)
A18: 月の予算はスマレジの月別予算（8月350万・12月700万など）。前提シートの年間予算を変えると同じ比率で配分し直す。
A19: 例：8月に実績売上3,600,000・実績粗利1,300,000を入れると、粗利予算比106.1%・スコア105.5%で第2段階になる。

Sheet 論点メモ
A1: 10/2 予算会議の論点
A3: 結論 | B3: 予算（税抜6,000万円・粗利2,100万円）は、新体制の損益分岐（5,896万円）を2%上回るだけ。予算100%で報奨金を払うと店舗の実費はちょうどトントン（+0.5万円）、110%で本部費込みでも黒字（+40万円）。
A4: 最大の前提 | B4: 粗利率35%。34.5%を切ると予算どおりでも赤字。前年並み31%なら−211万円。売上より粗利率が勝負。
A5: 人件費 | B5: 年960万円（月80万円）で計上。前年実額809万円から年151万円増。回収には粗利率35%で売上約537万円の上積みが必要。
A6: 本部費 | B6: 管理会計の共通費 月15.8万円（年189.6万円）。人員割の固定額で、店の努力では減らない。
A7: 報奨金の設計 | B7: 粗利額80%＋売上20%のスコア、単月判定、粗利額が予算未達なら0円。段階は予算比100/105/110%。支払いは夏冬の賞与にまとめる案（社保・扶養の確認）。
A8: 決めること | B8: ①予算6,000万円・粗利率35%で確定か ②報奨金の支給開始を予算100%に置くか ③金額表と対象人数 ④支払い方法 ⑤処分品とECの扱い ⑥値下げの決裁範囲
A9: 要確認 | B9: 管理諸費（11月398,379円）と租税公課（3月・7月）の中身を発展会計の元帳で確認。法定福利の料率（15.5%は仮置き）。8月・9月の実績。
