Workbook

Sheet 月別目標
A1: Weekends 2027年度 月別の目標と損益（2026年8月〜2027年7月）
A2: 金額は税抜・円。報奨金の判定はスマレジの粗利で行う。黄色の「実績粗利」を入れると、達成率と報奨金が出ます。
A3: 年間の売上目標 | B3: 年間の粗利目標 | C3: 粗利率 | D3: 営業利益 （全月100%達成） | E3: 営業利益 （全月105%達成） | F3: 報奨金・年 （全月100%達成） | G3: 報奨金・年 （全月105%達成）
A4: =年間損益!C6 -> 63000000 | B4: =年間損益!C7 -> 21500000 | C4: =年間損益!C8 -> 0.34126984 | D4: =年間損益!C15 -> 225776 | E4: =年間損益!D15 -> 842796 | F4: =年間損益!C10 -> 360000 | G4: =年間損益!D10 -> 600000
A6: 月 | B6: 前年売上 （実績） | C6: 店長の予算 （スマレジ） | D6: 構成比 （店長の予算） | E6: 売上目標 | F6: 粗利目標 （100%） | G6: 粗利目標 （105%） | H6: 営業利益 （100%達成時） | I6: 営業利益 の累計 | J6: 実績粗利 （スマレジ） | K6: 達成率 | L6: 報奨金 （店舗計）
A7: 8月 | B7: 3040292 | C7: 3500000 | D7: =C7/SUM($C$7:$C$18) -> 0.058333333 | E7: 3700000 | F7: 1250000 | G7: =ROUND(F7*年間損益!$B$38/50000,0)*50000 -> 1300000 | H7: =F7-E7*年間損益!$B$34-年間損益!$B$39/12-年間損益!$C$25 -> -415592 | I7: =SUM($H$7:H7) -> -415592 | K7: =IF(J7="","",J7/F7) | L7: =IF(J7="","",IF(J7>=G7,年間損益!$D$25,IF(J7>=F7,年間損益!$C$25,0)))
A8: 9月 | B8: 3638478 | C8: 4500000 | D8: =C8/SUM($C$7:$C$18) -> 0.075 | E8: 4700000 | F8: 1600000 | G8: =ROUND(F8*年間損益!$B$38/50000,0)*50000 -> 1700000 | H8: =F8-E8*年間損益!$B$34-年間損益!$B$39/12-年間損益!$C$25 -> -134792 | I8: =SUM($H$7:H8) -> -550384 | K8: =IF(J8="","",J8/F8) | L8: =IF(J8="","",IF(J8>=G8,年間損益!$D$25,IF(J8>=F8,年間損益!$C$25,0)))
A9: 10月 | B9: 4934704 | C9: 5500000 | D9: =C9/SUM($C$7:$C$18) -> 0.091666667 | E9: 5800000 | F9: 2000000 | G9: =ROUND(F9*年間損益!$B$38/50000,0)*50000 -> 2100000 | H9: =F9-E9*年間損益!$B$34-年間損益!$B$39/12-年間損益!$C$25 -> 189088 | I9: =SUM($H$7:H9) -> -361296 | K9: =IF(J9="","",J9/F9) | L9: =IF(J9="","",IF(J9>=G9,年間損益!$D$25,IF(J9>=F9,年間損益!$C$25,0)))
A10: 11月 | B10: 5149749 | C10: 5500000 | D10: =C10/SUM($C$7:$C$18) -> 0.091666667 | E10: 5800000 | F10: 2000000 | G10: =ROUND(F10*年間損益!$B$38/50000,0)*50000 -> 2100000 | H10: =F10-E10*年間損益!$B$34-年間損益!$B$39/12-年間損益!$C$25 -> 189088 | I10: =SUM($H$7:H10) -> -172208 | K10: =IF(J10="","",J10/F10) | L10: =IF(J10="","",IF(J10>=G10,年間損益!$D$25,IF(J10>=F10,年間損益!$C$25,0)))
A11: 12月 | B11: 6820952 | C11: 7000000 | D11: =C11/SUM($C$7:$C$18) -> 0.11666667 | E11: 7300000 | F11: 2500000 | G11: =ROUND(F11*年間損益!$B$38/50000,0)*50000 -> 2650000 | H11: =F11-E11*年間損益!$B$34-年間損益!$B$39/12-年間損益!$C$25 -> 585288 | I11: =SUM($H$7:H11) -> 413080 | K11: =IF(J11="","",J11/F11) | L11: =IF(J11="","",IF(J11>=G11,年間損益!$D$25,IF(J11>=F11,年間損益!$C$25,0)))
A12: 1月 | B12: 4850701 | C12: 6000000 | D12: =C12/SUM($C$7:$C$18) -> 0.1 | E12: 6300000 | F12: 2100000 | G12: =ROUND(F12*年間損益!$B$38/50000,0)*50000 -> 2200000 | H12: =F12-E12*年間損益!$B$34-年間損益!$B$39/12-年間損益!$C$25 -> 254488 | I12: =SUM($H$7:H12) -> 667568 | K12: =IF(J12="","",J12/F12) | L12: =IF(J12="","",IF(J12>=G12,年間損益!$D$25,IF(J12>=F12,年間損益!$C$25,0)))
A13: 2月 | B13: 2795656 | C13: 3500000 | D13: =C13/SUM($C$7:$C$18) -> 0.058333333 | E13: 3700000 | F13: 1250000 | G13: =ROUND(F13*年間損益!$B$38/50000,0)*50000 -> 1300000 | H13: =F13-E13*年間損益!$B$34-年間損益!$B$39/12-年間損益!$C$25 -> -415592 | I13: =SUM($H$7:H13) -> 251976 | K13: =IF(J13="","",J13/F13) | L13: =IF(J13="","",IF(J13>=G13,年間損益!$D$25,IF(J13>=F13,年間損益!$C$25,0)))
A14: 3月 | B14: 4419804 | C14: 5500000 | D14: =C14/SUM($C$7:$C$18) -> 0.091666667 | E14: 5800000 | F14: 2000000 | G14: =ROUND(F14*年間損益!$B$38/50000,0)*50000 -> 2100000 | H14: =F14-E14*年間損益!$B$34-年間損益!$B$39/12-年間損益!$C$25 -> 189088 | I14: =SUM($H$7:H14) -> 441064 | K14: =IF(J14="","",J14/F14) | L14: =IF(J14="","",IF(J14>=G14,年間損益!$D$25,IF(J14>=F14,年間損益!$C$25,0)))
A15: 4月 | B15: 3581469 | C15: 4500000 | D15: =C15/SUM($C$7:$C$18) -> 0.075 | E15: 4700000 | F15: 1600000 | G15: =ROUND(F15*年間損益!$B$38/50000,0)*50000 -> 1700000 | H15: =F15-E15*年間損益!$B$34-年間損益!$B$39/12-年間損益!$C$25 -> -134792 | I15: =SUM($H$7:H15) -> 306272 | K15: =IF(J15="","",J15/F15) | L15: =IF(J15="","",IF(J15>=G15,年間損益!$D$25,IF(J15>=F15,年間損益!$C$25,0)))
A16: 5月 | B16: 4799124 | C16: 4500000 | D16: =C16/SUM($C$7:$C$18) -> 0.075 | E16: 4700000 | F16: 1600000 | G16: =ROUND(F16*年間損益!$B$38/50000,0)*50000 -> 1700000 | H16: =F16-E16*年間損益!$B$34-年間損益!$B$39/12-年間損益!$C$25 -> -134792 | I16: =SUM($H$7:H16) -> 171480 | K16: =IF(J16="","",J16/F16) | L16: =IF(J16="","",IF(J16>=G16,年間損益!$D$25,IF(J16>=F16,年間損益!$C$25,0)))
A17: 6月 | B17: 4888307 | C17: 5500000 | D17: =C17/SUM($C$7:$C$18) -> 0.091666667 | E17: 5800000 | F17: 2000000 | G17: =ROUND(F17*年間損益!$B$38/50000,0)*50000 -> 2100000 | H17: =F17-E17*年間損益!$B$34-年間損益!$B$39/12-年間損益!$C$25 -> 189088 | I17: =SUM($H$7:H17) -> 360568 | K17: =IF(J17="","",J17/F17) | L17: =IF(J17="","",IF(J17>=G17,年間損益!$D$25,IF(J17>=F17,年間損益!$C$25,0)))
A18: 7月 | B18: 4741065 | C18: 4500000 | D18: =C18/SUM($C$7:$C$18) -> 0.075 | E18: 4700000 | F18: 1600000 | G18: =ROUND(F18*年間損益!$B$38/50000,0)*50000 -> 1700000 | H18: =F18-E18*年間損益!$B$34-年間損益!$B$39/12-年間損益!$C$25 -> -134792 | I18: =SUM($H$7:H18) -> 225776 | K18: =IF(J18="","",J18/F18) | L18: =IF(J18="","",IF(J18>=G18,年間損益!$D$25,IF(J18>=F18,年間損益!$C$25,0)))
A19: 年計 | B19: =SUM(B7:B18) -> 53660301 | C19: =SUM(C7:C18) -> 60000000 | D19: =SUM(D7:D18) -> 1 | E19: =SUM(E7:E18) -> 63000000 | F19: =SUM(F7:F18) -> 21500000 | G19: =SUM(G7:G18) -> 22650000 | H19: =SUM(H7:H18) -> 225776 | J19: =SUM(J7:J18) -> 0 | K19: =IF(COUNT(J7:J18)=0,"",J19/SUMIF(J7:J18,"<>",F7:F18)) | L19: =SUM(L7:L18) -> 0
A20: 年間目標との差 | E20: =E19-年間損益!B30 -> 0 | F20: =F19-年間損益!B31 -> 0
A22: ・売上目標と粗利目標は、店長がスマレジに登録した予算の比率で配分し、売上は10万円単位、粗利は5万円単位に丸めた（年計を予算に合わせてある。目標を手で変えたら「年間目標との差」を0にする）。
A23: ・営業利益は、その月の粗利目標をちょうど達成し報奨金3万円を払った場合。固定費（人件費・テナント固定分・その他の店舗経費・共通部の費用）は12等分した。
A24: ・報奨金は、その月の粗利が粗利目標の100%以上で店舗計3万円、105%以上で5万円。1人あたりの額は「年間損益」シートの「2. 報奨金のルール」。
A25: ・105%の粗利目標は月ごとに5万円単位で丸めたため、年計は2,265万円（2,150万円×105%＝2,257.5万円より7.5万円多い）。「年間損益」シートの105%欄は丸める前の2,257.5万円で計算している。
A26: ・達成率の年計は、実績を入れた月だけで計算する。

Sheet 年間損益
A1: Weekends 2027年度 年間の損益（PL）と報奨金のルール
A2: 金額は税抜・円。黄色のセルが入力値で、変えると2枚とも再計算されます。
A4: 1. 年間の損益（PL）
A5: 科目 | B5: 前年実績 （2025/8〜2026/7） | C5: 2027年度予算 （全月100%達成） | D5: 2027年度予算 （全月105%達成） | E5: 説明
A6: 売上高 | B6: 53660301 | C6: =$B$30 -> 63000000 | D6: =$B$30*$B$38 -> 66150000 | E6: 予算は年6,300万円。105%は売上も5%増えた場合
A7: 売上総利益（粗利） | B7: 16612146 | C7: =$B$31 -> 21500000 | D7: =$B$31*$B$38 -> 22575000 | E7: 前年は会計の粗利（棚卸の調整を含む）。報奨金の判定はスマレジの粗利で行う
A8: 粗利率 | B8: =B7/B6 -> 0.30957981 | C8: =C7/C6 -> 0.34126984 | D8: =D7/D6 -> 0.34126984
A9: 人件費（給与・賞与・法定福利） | B9: 8091567 | C9: =$B$32*12 -> 9600000 | D9: =$B$32*12 -> 9600000 | E9: 前年＝給与6,359,668＋賞与770,000＋法定福利961,899。予算は月80万円
A10: 報奨金 | B10: 0 | C10: =$C$25*12 -> 360000 | D10: =$D$25*12 -> 600000 | E10: 全月達成した場合。下の「2. 報奨金のルール」から計算
A11: テナント経費 | B11: 6230261 | C11: =$B$33*12+C6*$B$34 -> 6877104 | D11: =$B$33*12+D6*$B$34 -> 7095084 | E11: 売上歩合制：固定分（月）×12＋売上×連動率
A12: その他の店舗経費 | B12: 3493268 | C12: =$B$35 -> 3493268 | D12: =$B$35 -> 3493268 | E12: 管理諸費・減価償却・旅費・通信・消耗品など（発展会計 営業部）
A13: 共通部の費用 | B13: 943852 | C13: =$B$36 -> 943852 | D13: =$B$36 -> 943852 | E13: 租税公課882,500（3月・7月）、消耗品・保険料など。中身は確認中
A14: 販管費 計 | B14: =SUM(B9:B13) -> 18758948 | C14: =SUM(C9:C13) -> 21274224 | D14: =SUM(D9:D13) -> 21732204
A15: 営業利益 | B15: =B7-B14 -> -2146802 | C15: =C7-C14 -> 225776 | D15: =D7-D14 -> 842796
A16: 営業外損益 | B16: -153129 | C16: =-$B$37 -> -300000 | D16: =-$B$37 -> -300000 | E16: 前年＝受取利息・雑収入30,345−支払利息183,474。予算は費用30万円（社長案）
A17: 経常利益 | B17: =B15+B16 -> -2299931 | C17: =C15+C16 -> -74224 | D17: =D15+D16 -> 542796
A18: 損益分岐の売上（報奨金を払う前） | C18: =$B$39/($B$31/$B$30-$B$34) -> 60846965 | D18: =$B$39/($B$31/$B$30-$B$34) -> 60846965 | E18: これより売上が少ないと営業赤字（粗利率は予算どおりの場合）
A20: 2. 報奨金のルール（その月の粗利がスマレジで目標以上なら、その月に支給の判定）
A21: 区分 | B21: 人数 | C21: 粗利目標の100%以上 （1人・月） | D21: 粗利目標の105%以上 （1人・月）
A22: 店長 | B22: 1 | C22: 12000 | D22: 20000
A23: 古参パート | B23: 1 | C23: 8000 | D23: 14000
A24: その他パート | B24: 2 | C24: 5000 | D24: 8000
A25: 店舗計（月） | B25: =SUM(B22:B24) -> 4 | C25: =SUMPRODUCT($B$22:$B$24,C22:C24) -> 30000 | D25: =SUMPRODUCT($B$22:$B$24,D22:D24) -> 50000
A26: 全月達成した場合（年） | C26: =C25*12 -> 360000 | D26: =D25*12 -> 600000
A28: 3. 前提（入力値）
A29: 項目 | B29: 値 | C29: 出所・備考
A30: 年間の売上目標 | B30: 63000000 | C30: 検討案
A31: 年間の粗利目標 | B31: 21500000 | C31: 検討案（粗利率34.1%）
A32: 人件費（月） | B32: 800000 | C32: 給与・賞与・法定福利込み。報奨金は別枠
A33: テナント経費の固定分（月） | B33: 209792 | C33: 前年12か月の実績から算出（売上歩合制の固定部分）
A34: テナント経費の売上連動率 | B34: 0.0692 | C34: 同上（売上に比例する部分）
A35: その他の店舗経費（年） | B35: 3493268 | C35: 前年実績（発展会計 営業部）
A36: 共通部の費用（年） | B36: 943852 | C36: 前年実績（発展会計 全社−営業部）
A37: 営業外費用（年） | B37: 300000 | C37: 社長案
A38: 報奨金の上の段階のライン | B38: 1.05 | C38: 粗利目標の105%
A39: 年間の固定費（計算） | B39: =B32*12+B33*12+B35+B36 -> 16554624 | C39: 人件費＋テナント固定分＋その他の店舗経費＋共通部の費用
